subprocess_monitor/__init__.py
subprocess_monitor/__main__.py
subprocess_monitor/defaults.py
subprocess_monitor/helper.py
subprocess_monitor/subprocess_monitor.py
subprocess_monitor/types.py
subprocess_monitor/validation.py
subprocess_monitor-0.4.0.dist-info/METADATA
subprocess_monitor-0.4.0.dist-info/WHEEL
subprocess_monitor-0.4.0.dist-info/licenses/LICENSE
subprocess_monitor-0.4.0.dist-info/RECORD
