Metadata-Version: 2.4
Name: subprocess-monitor
Version: 0.4.0
Summary: A service to manage monitor and spawn subprocess
Author-email: JulianKimmig <julian.kimmig@gmx.net>
License: MIT
License-File: LICENSE
Requires-Python: >=3.9
Requires-Dist: aiohttp
Requires-Dist: psutil
